{
  "version": "1.0.0",
  "lastScanned": 1775355835424,
  "projectRoot": "c:\\Users\\bumen\\Desktop\\keyscape",
  "techStack": {
    "languages": [
      {
        "name": "JavaScript/TypeScript",
        "version": null,
        "confidence": "high",
        "markers": [
          "package.json"
        ]
      },
      {
        "name": "TypeScript",
        "version": null,
        "confidence": "high",
        "markers": [
          "tsconfig.json"
        ]
      }
    ],
    "frameworks": [
      {
        "name": "next",
        "version": "16.2.2",
        "category": "fullstack"
      },
      {
        "name": "react",
        "version": "19.2.4",
        "category": "frontend"
      },
      {
        "name": "react-dom",
        "version": "19.2.4",
        "category": "frontend"
      }
    ],
    "packageManager": "npm",
    "runtime": null
  },
  "build": {
    "buildCommand": "npm run build",
    "testCommand": null,
    "lintCommand": "npm run lint",
    "devCommand": "npm run dev",
    "scripts": {
      "dev": "next dev",
      "build": "next build",
      "start": "next start",
      "lint": "eslint"
    }
  },
  "conventions": {
    "namingStyle": "camelCase/PascalCase",
    "importStyle": "ES modules",
    "testPattern": null,
    "fileOrganization": null
  },
  "structure": {
    "isMonorepo": false,
    "workspaces": [],
    "mainDirectories": [
      "app",
      "components",
      "lib",
      "public"
    ],
    "gitBranches": null
  },
  "customNotes": [],
  "directoryMap": {
    "app": {
      "path": "app",
      "purpose": "Application code",
      "fileCount": 4,
      "lastAccessed": 1775355835376,
      "keyFiles": [
        "favicon.ico",
        "globals.css",
        "layout.tsx",
        "page.tsx"
      ]
    },
    "components": {
      "path": "components",
      "purpose": "UI components",
      "fileCount": 5,
      "lastAccessed": 1775355835377,
      "keyFiles": [
        "ControlBar.tsx",
        "PlaybackPlayer.tsx",
        "ShareButton.tsx",
        "TypingStage.tsx",
        "Visualizer.tsx"
      ]
    },
    "hooks": {
      "path": "hooks",
      "purpose": null,
      "fileCount": 3,
      "lastAccessed": 1775355835392,
      "keyFiles": [
        "useAudioEngine.ts",
        "useTypingCapture.ts",
        "useVisualizer.ts"
      ]
    },
    "lib": {
      "path": "lib",
      "purpose": "Library code",
      "fileCount": 4,
      "lastAccessed": 1775355835394,
      "keyFiles": [
        "audio-engine.ts",
        "note-mapper.ts",
        "share-codec.ts",
        "visualizer-engine.ts"
      ]
    },
    "public": {
      "path": "public",
      "purpose": "Public files",
      "fileCount": 5,
      "lastAccessed": 1775355835394,
      "keyFiles": [
        "file.svg",
        "globe.svg",
        "next.svg",
        "vercel.svg",
        "window.svg"
      ]
    },
    "types": {
      "path": "types",
      "purpose": "Type definitions",
      "fileCount": 1,
      "lastAccessed": 1775355835395,
      "keyFiles": [
        "index.ts"
      ]
    }
  },
  "hotPaths": [],
  "userDirectives": []
}